chris_plugin/__init__.py
chris_plugin/_atypes.py
chris_plugin/_registration.py
chris_plugin/chris_plugin.py
chris_plugin/constants.py
chris_plugin/helpers.py
chris_plugin/limits.py
chris_plugin/links.py
chris_plugin/main_function.py
chris_plugin/mapper.py
chris_plugin/parameters.py
chris_plugin/types.py
chris_plugin/tool/__init__.py
chris_plugin/tool/chris_plugin_info.py
chris_plugin/tool/image.py
chris_plugin-0.4.0.dist-info/LICENSE
chris_plugin-0.4.0.dist-info/METADATA
chris_plugin-0.4.0.dist-info/WHEEL
chris_plugin-0.4.0.dist-info/entry_points.txt
chris_plugin-0.4.0.dist-info/top_level.txt
chris_plugin-0.4.0.dist-info/RECORD
