Metadata-Version: 2.1
Name: chris-plugin
Version: 0.4.0
Summary: ChRIS plugin helper
Home-page: https://github.com/FNNDSC/chris_plugin
Author: Jennings Zhang
Author-email: dev@babyMRI.org
License: MIT
Project-URL: Documentation, https://fnndsc.github.io/chris_plugin/
Project-URL: Source, https://github.com/FNNDSC/chris_plugin
Project-URL: Tracker, https://github.com/FNNDSC/chris_plugin/issues
Classifier: Development Status :: 1 - Planning
Classifier: License :: OSI Approved :: MIT License
Classifier: Programming Language :: Python :: 3.8
Classifier: Programming Language :: Python :: 3.9
Classifier: Programming Language :: Python :: 3.10
Classifier: Programming Language :: Python :: 3.11
Classifier: Programming Language :: Python :: 3.12
Classifier: Topic :: Software Development
Classifier: Topic :: Scientific/Engineering
Classifier: Topic :: Scientific/Engineering :: Bio-Informatics
Classifier: Topic :: Scientific/Engineering :: Medical Science Apps.
Requires-Python: >= 3.8
License-File: LICENSE
Requires-Dist: importlib-metadata ; python_version < "3.10"
Provides-Extra: dev
Requires-Dist: pytest ~=7.2 ; extra == 'dev'
Requires-Dist: pytest-mock ~=3.10 ; extra == 'dev'
Requires-Dist: pytest-cov ~=4.0.0 ; extra == 'dev'
Provides-Extra: none
